{
	"format_version": "1.12.0",
	"minecraft:geometry": [
		{
			"description": {
				"identifier": "geometry.grip_cqr - Converted",
				"texture_width": 32,
				"texture_height": 32,
				"visible_bounds_width": 2,
				"visible_bounds_height": 1.5,
				"visible_bounds_offset": [0, 0.25, 0]
			},
			"bones": [
				{
					"name": "grip_cqr_g1",
					"pivot": [0, -0.1875, 5.11921],
					"cubes": [
						{
							"origin": [-0.5625, -0.5125, -2.88079],
							"size": [1.125, 0.5, 7.5],
							"uv": {
								"north": {"uv": [6, 16], "uv_size": [1, 0.5]},
								"east": {"uv": [2, 0], "uv_size": [7.5, 0.5]},
								"south": {"uv": [19, 3], "uv_size": [1, 0.5]},
								"west": {"uv": [2, 1], "uv_size": [7.5, 0.5]},
								"up": {"uv": [0, 0], "uv_size": [1, 7.5]},
								"down": {"uv": [1, 7.5], "uv_size": [1, -7.5]}
							}
						},
						{
							"origin": [-0.6125, -0.0125, -0.73079],
							"size": [1.225, 0.25, 0.25],
							"pivot": [0, -0.3875, -0.50579],
							"rotation": [45, 0, 0],
							"uv": {
								"north": {"uv": [19, 18], "uv_size": [1, 0.5]},
								"east": {"uv": [10, 22], "uv_size": [0.5, 0.5]},
								"south": {"uv": [19, 19], "uv_size": [1, 0.5]},
								"west": {"uv": [22, 10], "uv_size": [0.5, 0.5]},
								"up": {"uv": [0, 20], "uv_size": [1, 0.5]},
								"down": {"uv": [1, 20.5], "uv_size": [1, -0.5]}
							}
						},
						{
							"origin": [-0.6125, -2.0125, 1.2692],
							"size": [1.225, 0.25, 0.25],
							"pivot": [0, -0.3875, -0.50579],
							"rotation": [45, 0, 0],
							"uv": {
								"north": {"uv": [20, 1], "uv_size": [1, 0.5]},
								"east": {"uv": [11, 22], "uv_size": [0.5, 0.5]},
								"south": {"uv": [2, 20], "uv_size": [1, 0.5]},
								"west": {"uv": [22, 11], "uv_size": [0.5, 0.5]},
								"up": {"uv": [20, 2], "uv_size": [1, 0.5]},
								"down": {"uv": [3, 20.5], "uv_size": [1, -0.5]}
							}
						},
						{
							"origin": [-0.5625, -0.0125, -2.88079],
							"size": [1.125, 0.25, 2],
							"uv": {
								"north": {"uv": [20, 3], "uv_size": [1, 0.5]},
								"east": {"uv": [10, 3], "uv_size": [2, 0.5]},
								"south": {"uv": [4, 20], "uv_size": [1, 0.5]},
								"west": {"uv": [10, 5], "uv_size": [2, 0.5]},
								"up": {"uv": [7, 5], "uv_size": [1, 2]},
								"down": {"uv": [7, 9], "uv_size": [1, -2]}
							}
						},
						{
							"origin": [-0.5625, -0.0125, 1.86921],
							"size": [1.125, 0.25, 2.5],
							"uv": {
								"north": {"uv": [20, 4], "uv_size": [1, 0.5]},
								"east": {"uv": [3, 9], "uv_size": [2.5, 0.5]},
								"south": {"uv": [5, 20], "uv_size": [1, 0.5]},
								"west": {"uv": [9, 4], "uv_size": [2.5, 0.5]},
								"up": {"uv": [2, 6], "uv_size": [1, 2.5]},
								"down": {"uv": [3, 8.5], "uv_size": [1, -2.5]}
							}
						},
						{
							"origin": [-0.5615, -0.85977, 1.8237],
							"size": [1.123, 0.25, 0.5],
							"pivot": [0, -0.73477, 1.0737],
							"rotation": [45, 0, 0],
							"uv": {
								"north": {"uv": [20, 5], "uv_size": [1, 0.5]},
								"east": {"uv": [12, 22], "uv_size": [0.5, 0.5]},
								"south": {"uv": [6, 20], "uv_size": [1, 0.5]},
								"west": {"uv": [22, 12], "uv_size": [0.5, 0.5]},
								"up": {"uv": [20, 6], "uv_size": [1, 0.5]},
								"down": {"uv": [7, 20.5], "uv_size": [1, -0.5]}
							}
						},
						{
							"origin": [-0.5615, -0.17407, 4.22901],
							"size": [1.123, 0.3535, 0.25],
							"pivot": [0, 0.07593, 4.35401],
							"rotation": [45, 0, 0],
							"uv": {
								"north": {"uv": [20, 7], "uv_size": [1, 0.5]},
								"east": {"uv": [13, 22], "uv_size": [0.5, 0.5]},
								"south": {"uv": [8, 20], "uv_size": [1, 0.5]},
								"west": {"uv": [22, 13], "uv_size": [0.5, 0.5]},
								"up": {"uv": [20, 8], "uv_size": [1, 0.5]},
								"down": {"uv": [9, 20.5], "uv_size": [1, -0.5]}
							}
						},
						{
							"origin": [-0.5615, 3.45522, 0.54089],
							"size": [1.123, 0.3535, 0.25],
							"pivot": [0, 0.00522, 4.26589],
							"rotation": [45, 0, 0],
							"uv": {
								"north": {"uv": [20, 9], "uv_size": [1, 0.5]},
								"east": {"uv": [14, 22], "uv_size": [0.5, 0.5]},
								"south": {"uv": [10, 20], "uv_size": [1, 0.5]},
								"west": {"uv": [22, 14], "uv_size": [0.5, 0.5]},
								"up": {"uv": [20, 10], "uv_size": [1, 0.5]},
								"down": {"uv": [11, 20.5], "uv_size": [1, -0.5]}
							}
						},
						{
							"origin": [-0.5625, -2.3875, -0.38079],
							"size": [1.125, 1.875, 1.25],
							"uv": {
								"north": {"uv": [0, 8], "uv_size": [1, 2]},
								"east": {"uv": [5, 2], "uv_size": [1.5, 2]},
								"south": {"uv": [1, 8], "uv_size": [1, 2]},
								"west": {"uv": [5, 4], "uv_size": [1.5, 2]},
								"up": {"uv": [8, 2], "uv_size": [1, 1.5]},
								"down": {"uv": [8, 5.5], "uv_size": [1, -1.5]}
							}
						},
						{
							"origin": [-0.5615, -1.6625, 0.21921],
							"size": [1.123, 0.75, 0.5],
							"pivot": [0, -1.5125, 1.5442],
							"rotation": [-45, 0, 0],
							"uv": {
								"north": {"uv": [10, 6], "uv_size": [1, 1]},
								"east": {"uv": [20, 11], "uv_size": [0.5, 1]},
								"south": {"uv": [10, 7], "uv_size": [1, 1]},
								"west": {"uv": [12, 20], "uv_size": [0.5, 1]},
								"up": {"uv": [20, 12], "uv_size": [1, 0.5]},
								"down": {"uv": [13, 20.5], "uv_size": [1, -0.5]}
							}
						},
						{
							"origin": [-0.5615, -1.2125, 0.06921],
							"size": [1.123, 0.75, 0.5],
							"pivot": [0, -1.5125, -0.35579],
							"rotation": [45, 0, 0],
							"uv": {
								"north": {"uv": [8, 10], "uv_size": [1, 1]},
								"east": {"uv": [20, 13], "uv_size": [0.5, 1]},
								"south": {"uv": [10, 8], "uv_size": [1, 1]},
								"west": {"uv": [14, 20], "uv_size": [0.5, 1]},
								"up": {"uv": [20, 14], "uv_size": [1, 0.5]},
								"down": {"uv": [15, 20.5], "uv_size": [1, -0.5]}
							}
						},
						{
							"origin": [-0.6125, -0.35184, -0.76302],
							"size": [1.225, 0.25, 0.25],
							"pivot": [-0.1, -0.45184, 2.01198],
							"rotation": [45, 0, 0],
							"uv": {
								"north": {"uv": [20, 15], "uv_size": [1, 0.5]},
								"east": {"uv": [15, 22], "uv_size": [0.5, 0.5]},
								"south": {"uv": [16, 20], "uv_size": [1, 0.5]},
								"west": {"uv": [22, 15], "uv_size": [0.5, 0.5]},
								"up": {"uv": [20, 16], "uv_size": [1, 0.5]},
								"down": {"uv": [17, 20.5], "uv_size": [1, -0.5]}
							}
						},
						{
							"origin": [-0.6125, -3.84352, 1.69981],
							"size": [1.225, 0.25, 0.25],
							"pivot": [0, -3.56852, 1.67481],
							"rotation": [-22.5, 0, 0],
							"uv": {
								"north": {"uv": [20, 17], "uv_size": [1, 0.5]},
								"east": {"uv": [16, 22], "uv_size": [0.5, 0.5]},
								"south": {"uv": [20, 18], "uv_size": [1, 0.5]},
								"west": {"uv": [22, 16], "uv_size": [0.5, 0.5]},
								"up": {"uv": [19, 20], "uv_size": [1, 0.5]},
								"down": {"uv": [20, 19.5], "uv_size": [1, -0.5]}
							}
						},
						{
							"origin": [-0.3625, -3.45184, 2.38698],
							"size": [0.725, 0.25, 0.25],
							"pivot": [0, -0.45184, 2.01198],
							"rotation": [45, 0, 0],
							"uv": {
								"north": {"uv": [17, 22], "uv_size": [0.5, 0.5]},
								"east": {"uv": [22, 17], "uv_size": [0.5, 0.5]},
								"south": {"uv": [18, 22], "uv_size": [0.5, 0.5]},
								"west": {"uv": [22, 18], "uv_size": [0.5, 0.5]},
								"up": {"uv": [19, 22], "uv_size": [0.5, 0.5]},
								"down": {"uv": [22, 19.5], "uv_size": [0.5, -0.5]}
							}
						},
						{
							"origin": [-0.3625, -3.45184, 0.53698],
							"size": [0.725, 0.25, 0.25],
							"pivot": [0, -0.45184, 2.01198],
							"rotation": [45, 0, 0],
							"uv": {
								"north": {"uv": [20, 22], "uv_size": [0.5, 0.5]},
								"east": {"uv": [22, 20], "uv_size": [0.5, 0.5]},
								"south": {"uv": [21, 22], "uv_size": [0.5, 0.5]},
								"west": {"uv": [22, 21], "uv_size": [0.5, 0.5]},
								"up": {"uv": [22, 22], "uv_size": [0.5, 0.5]},
								"down": {"uv": [0, 23.5], "uv_size": [0.5, -0.5]}
							}
						},
						{
							"origin": [-0.5635, -4.49406, -0.81472],
							"size": [1.127, 1.4, 2.5],
							"inflate": 0.002,
							"pivot": [0, -3.74406, 1.99777],
							"rotation": [-45, 0, 0],
							"uv": {
								"north": {"uv": [8, 6], "uv_size": [1, 1.5]},
								"east": {"uv": [2, 2], "uv_size": [2.5, 1.5]},
								"south": {"uv": [8, 8], "uv_size": [1, 1.5]},
								"west": {"uv": [2, 4], "uv_size": [2.5, 1.5]},
								"up": {"uv": [4, 6], "uv_size": [1, 2.5]},
								"down": {"uv": [5, 8.5], "uv_size": [1, -2.5]}
							}
						},
						{
							"origin": [-0.13125, -4.53955, 1.73261],
							"size": [0.2625, 0.25, 0.85],
							"uv": {
								"north": {"uv": [23, 0], "uv_size": [0.5, 0.5]},
								"east": {"uv": [20, 20], "uv_size": [1, 0.5]},
								"south": {"uv": [1, 23], "uv_size": [0.5, 0.5]},
								"west": {"uv": [0, 21], "uv_size": [1, 0.5]},
								"up": {"uv": [21, 0], "uv_size": [0.5, 1]},
								"down": {"uv": [1, 22], "uv_size": [0.5, -1]}
							}
						},
						{
							"origin": [-0.13125, -3.88955, 2.08261],
							"size": [0.2625, 0.25, 1],
							"uv": {
								"north": {"uv": [23, 1], "uv_size": [0.5, 0.5]},
								"east": {"uv": [21, 1], "uv_size": [1, 0.5]},
								"south": {"uv": [2, 23], "uv_size": [0.5, 0.5]},
								"west": {"uv": [2, 21], "uv_size": [1, 0.5]},
								"up": {"uv": [21, 2], "uv_size": [0.5, 1]},
								"down": {"uv": [3, 22], "uv_size": [0.5, -1]}
							}
						},
						{
							"origin": [-0.13025, -4.59761, 2.72278],
							"size": [0.2605, 1.25, 0.25],
							"pivot": [-0.03125, -4.09761, 2.84778],
							"rotation": [-45, 0, 0],
							"uv": {
								"north": {"uv": [1, 15], "uv_size": [0.5, 1.5]},
								"east": {"uv": [2, 15], "uv_size": [0.5, 1.5]},
								"south": {"uv": [15, 2], "uv_size": [0.5, 1.5]},
								"west": {"uv": [3, 15], "uv_size": [0.5, 1.5]},
								"up": {"uv": [23, 2], "uv_size": [0.5, 0.5]},
								"down": {"uv": [3, 23.5], "uv_size": [0.5, -0.5]}
							}
						},
						{
							"origin": [-0.13025, -4.47387, 1.7755],
							"size": [0.2605, 1, 0.5],
							"pivot": [-0.03125, -3.97387, 2.0255],
							"rotation": [-45, 0, 0],
							"uv": {
								"north": {"uv": [21, 3], "uv_size": [0.5, 1]},
								"east": {"uv": [4, 21], "uv_size": [0.5, 1]},
								"south": {"uv": [21, 4], "uv_size": [0.5, 1]},
								"west": {"uv": [5, 21], "uv_size": [0.5, 1]},
								"up": {"uv": [23, 3], "uv_size": [0.5, 0.5]},
								"down": {"uv": [4, 23.5], "uv_size": [0.5, -0.5]}
							}
						},
						{
							"origin": [-0.3125, -3.72849, 1.52821],
							"size": [0.625, 0.5, 1.70313],
							"uv": {
								"north": {"uv": [23, 4], "uv_size": [0.5, 0.5]},
								"east": {"uv": [5, 15], "uv_size": [1.5, 0.5]},
								"south": {"uv": [5, 23], "uv_size": [0.5, 0.5]},
								"west": {"uv": [15, 5], "uv_size": [1.5, 0.5]},
								"up": {"uv": [15, 6], "uv_size": [0.5, 1.5]},
								"down": {"uv": [7, 16.5], "uv_size": [0.5, -1.5]}
							}
						},
						{
							"origin": [0.25, -3.90527, 1.52821],
							"size": [0.0625, 0.17678, 1.70312],
							"pivot": [0.3125, -3.72849, 2.37978],
							"rotation": [0, 0, 45],
							"uv": {
								"north": {"uv": [11, 24], "uv_size": [0.5, 0.5]},
								"east": {"uv": [18, 4], "uv_size": [1.5, 0.5]},
								"south": {"uv": [24, 11], "uv_size": [0.5, 0.5]},
								"west": {"uv": [18, 13], "uv_size": [1.5, 0.5]},
								"up": {"uv": [14, 18], "uv_size": [0.5, 1.5]},
								"down": {"uv": [18, 15.5], "uv_size": [0.5, -1.5]}
							}
						},
						{
							"origin": [-0.3115, -3.40055, 2.88523],
							"size": [0.624, 0.50417, 2.14022],
							"pivot": [0, -3.14638, 3.455],
							"rotation": [45, 0, 0],
							"uv": {
								"north": {"uv": [23, 5], "uv_size": [0.5, 0.5]},
								"east": {"uv": [10, 9], "uv_size": [2, 0.5]},
								"south": {"uv": [6, 23], "uv_size": [0.5, 0.5]},
								"west": {"uv": [10, 10], "uv_size": [2, 0.5]},
								"up": {"uv": [11, 0], "uv_size": [0.5, 2]},
								"down": {"uv": [2, 13], "uv_size": [0.5, -2]}
							}
						},
						{
							"origin": [0.1875, -3.14687, 2.91841],
							"size": [0.12363, 0.17457, 2.14789],
							"pivot": [0.3125, -2.97231, 3.98852],
							"rotation": [34.90697, -30.43111, 35.9746],
							"uv": {
								"north": {"uv": [12, 24], "uv_size": [0.5, 0.5]},
								"east": {"uv": [9, 14], "uv_size": [2, 0.5]},
								"south": {"uv": [24, 12], "uv_size": [0.5, 0.5]},
								"west": {"uv": [11, 14], "uv_size": [2, 0.5]},
								"up": {"uv": [14, 11], "uv_size": [0.5, 2]},
								"down": {"uv": [13, 16], "uv_size": [0.5, -2]}
							}
						},
						{
							"origin": [-0.5625, -0.79375, 4.11921],
							"size": [1.125, 0.28125, 0.75],
							"uv": {
								"north": {"uv": [21, 5], "uv_size": [1, 0.5]},
								"east": {"uv": [6, 21], "uv_size": [1, 0.5]},
								"south": {"uv": [21, 6], "uv_size": [1, 0.5]},
								"west": {"uv": [7, 21], "uv_size": [1, 0.5]},
								"up": {"uv": [11, 2], "uv_size": [1, 1]},
								"down": {"uv": [11, 7], "uv_size": [1, -1]}
							}
						},
						{
							"origin": [-0.3125, -2.21563, 4.24521],
							"size": [0.625, 1.45313, 0.5],
							"uv": {
								"north": {"uv": [8, 15], "uv_size": [0.5, 1.5]},
								"east": {"uv": [15, 8], "uv_size": [0.5, 1.5]},
								"south": {"uv": [9, 15], "uv_size": [0.5, 1.5]},
								"west": {"uv": [10, 15], "uv_size": [0.5, 1.5]},
								"up": {"uv": [23, 6], "uv_size": [0.5, 0.5]},
								"down": {"uv": [7, 23.5], "uv_size": [0.5, -0.5]}
							}
						},
						{
							"origin": [0.125, -2.21563, 4.74521],
							"size": [0.1875, 1.45313, 0.17678],
							"pivot": [0.3125, -1.48906, 4.74521],
							"rotation": [0, -45, 0],
							"uv": {
								"north": {"uv": [15, 18], "uv_size": [0.5, 1.5]},
								"east": {"uv": [16, 18], "uv_size": [0.5, 1.5]},
								"south": {"uv": [17, 18], "uv_size": [0.5, 1.5]},
								"west": {"uv": [18, 17], "uv_size": [0.5, 1.5]},
								"up": {"uv": [13, 24], "uv_size": [0.5, 0.5]},
								"down": {"uv": [24, 13.5], "uv_size": [0.5, -0.5]}
							}
						},
						{
							"origin": [-0.3125, -2.21563, 4.74521],
							"size": [0.1875, 1.45313, 0.17678],
							"pivot": [-0.3125, -1.48906, 4.74521],
							"rotation": [0, 45, 0],
							"uv": {
								"north": {"uv": [19, 7], "uv_size": [0.5, 1.5]},
								"east": {"uv": [19, 9], "uv_size": [0.5, 1.5]},
								"south": {"uv": [19, 11], "uv_size": [0.5, 1.5]},
								"west": {"uv": [19, 14], "uv_size": [0.5, 1.5]},
								"up": {"uv": [16, 24], "uv_size": [0.5, 0.5]},
								"down": {"uv": [24, 16.5], "uv_size": [0.5, -0.5]}
							}
						},
						{
							"origin": [-0.31113, -3.14687, 2.91841],
							"size": [0.12363, 0.17457, 2.14789],
							"pivot": [-0.3125, -2.97231, 3.98852],
							"rotation": [34.90697, 30.43111, -35.9746],
							"uv": {
								"north": {"uv": [15, 24], "uv_size": [0.5, 0.5]},
								"east": {"uv": [14, 13], "uv_size": [2, 0.5]},
								"south": {"uv": [24, 15], "uv_size": [0.5, 0.5]},
								"west": {"uv": [14, 14], "uv_size": [2, 0.5]},
								"up": {"uv": [0, 15], "uv_size": [0.5, 2]},
								"down": {"uv": [15, 2], "uv_size": [0.5, -2]}
							}
						},
						{
							"origin": [-0.3125, -3.90527, 1.52821],
							"size": [0.0625, 0.17678, 1.70312],
							"pivot": [-0.3125, -3.72849, 2.37978],
							"rotation": [0, 0, -45],
							"uv": {
								"north": {"uv": [14, 24], "uv_size": [0.5, 0.5]},
								"east": {"uv": [0, 19], "uv_size": [1.5, 0.5]},
								"south": {"uv": [24, 14], "uv_size": [0.5, 0.5]},
								"west": {"uv": [19, 0], "uv_size": [1.5, 0.5]},
								"up": {"uv": [19, 1], "uv_size": [0.5, 1.5]},
								"down": {"uv": [19, 6.5], "uv_size": [0.5, -1.5]}
							}
						},
						{
							"origin": [-0.1875, -2.2625, 4.24521],
							"size": [0.375, 1.5, 0.625],
							"uv": {
								"north": {"uv": [10, 18], "uv_size": [0.5, 1.5]},
								"east": {"uv": [11, 18], "uv_size": [0.5, 1.5]},
								"south": {"uv": [12, 18], "uv_size": [0.5, 1.5]},
								"west": {"uv": [13, 18], "uv_size": [0.5, 1.5]},
								"up": {"uv": [10, 24], "uv_size": [0.5, 0.5]},
								"down": {"uv": [24, 10.5], "uv_size": [0.5, -0.5]}
							}
						},
						{
							"origin": [-0.1865, -3.52138, 2.82999],
							"size": [0.373, 0.625, 2.25],
							"pivot": [0, -3.14638, 3.455],
							"rotation": [45, 0, 0],
							"uv": {
								"north": {"uv": [9, 24], "uv_size": [0.5, 0.5]},
								"east": {"uv": [14, 4], "uv_size": [2, 0.5]},
								"south": {"uv": [24, 9], "uv_size": [0.5, 0.5]},
								"west": {"uv": [5, 14], "uv_size": [2, 0.5]},
								"up": {"uv": [14, 5], "uv_size": [0.5, 2]},
								"down": {"uv": [14, 9], "uv_size": [0.5, -2]}
							}
						},
						{
							"origin": [-0.1875, -3.85349, 1.52821],
							"size": [0.375, 0.625, 1.75],
							"uv": {
								"north": {"uv": [8, 24], "uv_size": [0.5, 0.5]},
								"east": {"uv": [13, 10], "uv_size": [2, 0.5]},
								"south": {"uv": [24, 8], "uv_size": [0.5, 0.5]},
								"west": {"uv": [1, 14], "uv_size": [2, 0.5]},
								"up": {"uv": [14, 1], "uv_size": [0.5, 2]},
								"down": {"uv": [4, 16], "uv_size": [0.5, -2]}
							}
						},
						{
							"origin": [-0.1875, -3.22849, 1.52821],
							"size": [0.375, 0.125, 1.75],
							"uv": {
								"north": {"uv": [1, 24], "uv_size": [0.5, 0.5]},
								"east": {"uv": [7, 12], "uv_size": [2, 0.5]},
								"south": {"uv": [24, 1], "uv_size": [0.5, 0.5]},
								"west": {"uv": [12, 8], "uv_size": [2, 0.5]},
								"up": {"uv": [9, 12], "uv_size": [0.5, 2]},
								"down": {"uv": [12, 11], "uv_size": [0.5, -2]}
							}
						},
						{
							"origin": [0.1875, -3.22849, 1.52821],
							"size": [0.17188, 0.125, 1.75],
							"pivot": [0.1875, -3.10349, 2.40322],
							"rotation": [0, 0, 45],
							"uv": {
								"north": {"uv": [2, 24], "uv_size": [0.5, 0.5]},
								"east": {"uv": [10, 12], "uv_size": [2, 0.5]},
								"south": {"uv": [24, 2], "uv_size": [0.5, 0.5]},
								"west": {"uv": [12, 11], "uv_size": [2, 0.5]},
								"up": {"uv": [12, 12], "uv_size": [0.5, 2]},
								"down": {"uv": [0, 15], "uv_size": [0.5, -2]}
							}
						},
						{
							"origin": [-0.1865, -2.89638, 2.82999],
							"size": [0.373, 0.125, 2.25],
							"pivot": [0, -3.14638, 3.455],
							"rotation": [45, 0, 0],
							"uv": {
								"north": {"uv": [0, 24], "uv_size": [0.5, 0.5]},
								"east": {"uv": [12, 4], "uv_size": [2, 0.5]},
								"south": {"uv": [24, 0], "uv_size": [0.5, 0.5]},
								"west": {"uv": [12, 5], "uv_size": [2, 0.5]},
								"up": {"uv": [6, 12], "uv_size": [0.5, 2]},
								"down": {"uv": [12, 8], "uv_size": [0.5, -2]}
							}
						},
						{
							"origin": [0.1865, -2.65266, 2.65276],
							"size": [0.17188, 0.125, 2.01562],
							"pivot": [0.1865, -2.52766, 3.54338],
							"rotation": [35.26439, -30, 35.26439],
							"uv": {
								"north": {"uv": [3, 24], "uv_size": [0.5, 0.5]},
								"east": {"uv": [13, 0], "uv_size": [2, 0.5]},
								"south": {"uv": [24, 3], "uv_size": [0.5, 0.5]},
								"west": {"uv": [1, 13], "uv_size": [2, 0.5]},
								"up": {"uv": [13, 1], "uv_size": [0.5, 2]},
								"down": {"uv": [3, 15], "uv_size": [0.5, -2]}
							}
						},
						{
							"origin": [-0.1875, -2.2625, 4.12021],
							"size": [0.375, 1.5, 0.125],
							"uv": {
								"north": {"uv": [18, 0], "uv_size": [0.5, 1.5]},
								"east": {"uv": [2, 18], "uv_size": [0.5, 1.5]},
								"south": {"uv": [18, 2], "uv_size": [0.5, 1.5]},
								"west": {"uv": [3, 18], "uv_size": [0.5, 1.5]},
								"up": {"uv": [23, 22], "uv_size": [0.5, 0.5]},
								"down": {"uv": [23, 23.5], "uv_size": [0.5, -0.5]}
							}
						},
						{
							"origin": [0.1875, -2.0125, 4.12021],
							"size": [0.17188, 1.25, 0.25],
							"pivot": [0.1875, -1.5125, 4.12021],
							"rotation": [0, -45, 0],
							"uv": {
								"north": {"uv": [4, 18], "uv_size": [0.5, 1.5]},
								"east": {"uv": [5, 18], "uv_size": [0.5, 1.5]},
								"south": {"uv": [6, 18], "uv_size": [0.5, 1.5]},
								"west": {"uv": [18, 6], "uv_size": [0.5, 1.5]},
								"up": {"uv": [4, 24], "uv_size": [0.5, 0.5]},
								"down": {"uv": [24, 4.5], "uv_size": [0.5, -0.5]}
							}
						},
						{
							"origin": [-0.35937, -2.0125, 4.12021],
							"size": [0.17188, 1.25, 0.25],
							"pivot": [-0.1875, -1.5125, 4.12021],
							"rotation": [0, 45, 0],
							"uv": {
								"north": {"uv": [7, 18], "uv_size": [0.5, 1.5]},
								"east": {"uv": [8, 18], "uv_size": [0.5, 1.5]},
								"south": {"uv": [18, 8], "uv_size": [0.5, 1.5]},
								"west": {"uv": [9, 18], "uv_size": [0.5, 1.5]},
								"up": {"uv": [7, 24], "uv_size": [0.5, 0.5]},
								"down": {"uv": [24, 7.5], "uv_size": [0.5, -0.5]}
							}
						},
						{
							"origin": [-0.35837, -2.65266, 2.65276],
							"size": [0.17188, 0.125, 2.01562],
							"pivot": [-0.1865, -2.52766, 3.54338],
							"rotation": [35.26439, 30, -35.26439],
							"uv": {
								"north": {"uv": [6, 24], "uv_size": [0.5, 0.5]},
								"east": {"uv": [13, 9], "uv_size": [2, 0.5]},
								"south": {"uv": [24, 6], "uv_size": [0.5, 0.5]},
								"west": {"uv": [10, 13], "uv_size": [2, 0.5]},
								"up": {"uv": [8, 13], "uv_size": [0.5, 2]},
								"down": {"uv": [13, 14], "uv_size": [0.5, -2]}
							}
						},
						{
							"origin": [-0.35937, -3.22849, 1.52821],
							"size": [0.17188, 0.125, 1.75],
							"pivot": [-0.1875, -3.10349, 2.40322],
							"rotation": [0, 0, -45],
							"uv": {
								"north": {"uv": [5, 24], "uv_size": [0.5, 0.5]},
								"east": {"uv": [13, 3], "uv_size": [2, 0.5]},
								"south": {"uv": [24, 5], "uv_size": [0.5, 0.5]},
								"west": {"uv": [4, 13], "uv_size": [2, 0.5]},
								"up": {"uv": [13, 6], "uv_size": [0.5, 2]},
								"down": {"uv": [7, 15], "uv_size": [0.5, -2]}
							}
						},
						{
							"origin": [-0.5625, -1.4096, 4.35599],
							"size": [1.125, 0.3971, 0.26321],
							"pivot": [0, -1.3875, 3.49421],
							"rotation": [45, 0, 0],
							"uv": {
								"north": {"uv": [21, 7], "uv_size": [1, 0.5]},
								"east": {"uv": [23, 7], "uv_size": [0.5, 0.5]},
								"south": {"uv": [8, 21], "uv_size": [1, 0.5]},
								"west": {"uv": [8, 23], "uv_size": [0.5, 0.5]},
								"up": {"uv": [21, 8], "uv_size": [1, 0.5]},
								"down": {"uv": [9, 21.5], "uv_size": [1, -0.5]}
							}
						},
						{
							"origin": [0.04733, -1.10089, 4.1182],
							"size": [0.37879, 0.5221, 0.751],
							"pivot": [0.23483, -0.85089, 4.49421],
							"rotation": [0, 0, 45],
							"uv": {
								"north": {"uv": [23, 8], "uv_size": [0.5, 0.5]},
								"east": {"uv": [21, 9], "uv_size": [1, 0.5]},
								"south": {"uv": [9, 23], "uv_size": [0.5, 0.5]},
								"west": {"uv": [10, 21], "uv_size": [1, 0.5]},
								"up": {"uv": [21, 10], "uv_size": [0.5, 1]},
								"down": {"uv": [11, 22], "uv_size": [0.5, -1]}
							}
						},
						{
							"origin": [-0.42613, -1.10089, 4.1182],
							"size": [0.37879, 0.52209, 0.751],
							"pivot": [-0.23484, -0.85089, 4.49421],
							"rotation": [0, 0, -45],
							"uv": {
								"north": {"uv": [23, 9], "uv_size": [0.5, 0.5]},
								"east": {"uv": [21, 11], "uv_size": [1, 0.5]},
								"south": {"uv": [10, 23], "uv_size": [0.5, 0.5]},
								"west": {"uv": [12, 21], "uv_size": [1, 0.5]},
								"up": {"uv": [21, 12], "uv_size": [0.5, 1]},
								"down": {"uv": [13, 22], "uv_size": [0.5, -1]}
							}
						},
						{
							"origin": [-0.5615, -0.65262, 4.5308],
							"size": [1.123, 0.3535, 0.25],
							"pivot": [0, -0.47587, 4.6558],
							"rotation": [45, 0, 0],
							"uv": {
								"north": {"uv": [21, 13], "uv_size": [1, 0.5]},
								"east": {"uv": [23, 10], "uv_size": [0.5, 0.5]},
								"south": {"uv": [14, 21], "uv_size": [1, 0.5]},
								"west": {"uv": [11, 23], "uv_size": [0.5, 0.5]},
								"up": {"uv": [21, 14], "uv_size": [1, 0.5]},
								"down": {"uv": [15, 21.5], "uv_size": [1, -0.5]}
							}
						},
						{
							"origin": [-0.3145, -2.45184, -1.35947],
							"size": [0.62501, 2.49459, 0.99644],
							"pivot": [-0.1, -0.45184, 2.01198],
							"rotation": [45, 0, 0],
							"uv": {
								"north": {"uv": [9, 5], "uv_size": [0.5, 2.5]},
								"east": {"uv": [6, 6], "uv_size": [1, 2.5]},
								"south": {"uv": [6, 9], "uv_size": [0.5, 2.5]},
								"west": {"uv": [7, 2], "uv_size": [1, 2.5]},
								"up": {"uv": [8, 22], "uv_size": [0.5, 1]},
								"down": {"uv": [22, 9], "uv_size": [0.5, -1]}
							}
						},
						{
							"origin": [0.127, -4.68116, 0.15582],
							"size": [0.18215, 2.55709, 0.37993],
							"pivot": [0.3145, -3.36866, 0.15582],
							"rotation": [53.27495, 28.08945, 32.25672],
							"uv": {
								"north": {"uv": [7, 9], "uv_size": [0.5, 2.5]},
								"east": {"uv": [9, 8], "uv_size": [0.5, 2.5]},
								"south": {"uv": [0, 10], "uv_size": [0.5, 2.5]},
								"west": {"uv": [10, 0], "uv_size": [0.5, 2.5]},
								"up": {"uv": [20, 24], "uv_size": [0.5, 0.5]},
								"down": {"uv": [24, 20.5], "uv_size": [0.5, -0.5]}
							}
						},
						{
							"origin": [-0.30915, -4.68116, 0.15582],
							"size": [0.18215, 2.55709, 0.37993],
							"pivot": [-0.3145, -3.36866, 0.15582],
							"rotation": [53.27495, -28.08945, -32.25672],
							"uv": {
								"north": {"uv": [1, 10], "uv_size": [0.5, 2.5]},
								"east": {"uv": [3, 10], "uv_size": [0.5, 2.5]},
								"south": {"uv": [4, 10], "uv_size": [0.5, 2.5]},
								"west": {"uv": [5, 10], "uv_size": [0.5, 2.5]},
								"up": {"uv": [21, 24], "uv_size": [0.5, 0.5]},
								"down": {"uv": [24, 21.5], "uv_size": [0.5, -0.5]}
							}
						},
						{
							"origin": [-0.3155, -4.59335, 1.27099],
							"size": [0.62601, 0.99671, 0.74864],
							"pivot": [-0.1, -3.84664, 2.01963],
							"rotation": [-22.5, 0, 0],
							"uv": {
								"north": {"uv": [6, 22], "uv_size": [0.5, 1]},
								"east": {"uv": [22, 6], "uv_size": [0.5, 1]},
								"south": {"uv": [7, 22], "uv_size": [0.5, 1]},
								"west": {"uv": [22, 7], "uv_size": [0.5, 1]},
								"up": {"uv": [19, 24], "uv_size": [0.5, 0.5]},
								"down": {"uv": [24, 19.5], "uv_size": [0.5, -0.5]}
							}
						},
						{
							"origin": [0.12301, -4.39327, 1.1272],
							"size": [0.18743, 0.36263, 0.63517],
							"pivot": [0.31051, -4.39327, 1.38805],
							"rotation": [-16.52573, 15.48778, 41.98733],
							"uv": {
								"north": {"uv": [22, 24], "uv_size": [0.5, 0.5]},
								"east": {"uv": [24, 22], "uv_size": [0.5, 0.5]},
								"south": {"uv": [23, 24], "uv_size": [0.5, 0.5]},
								"west": {"uv": [24, 23], "uv_size": [0.5, 0.5]},
								"up": {"uv": [24, 24], "uv_size": [0.5, 0.5]},
								"down": {"uv": [0, 25.5], "uv_size": [0.5, -0.5]}
							}
						},
						{
							"origin": [-0.31044, -4.39327, 1.1272],
							"size": [0.18743, 0.36263, 0.63517],
							"pivot": [-0.31051, -4.39327, 1.38805],
							"rotation": [-16.52573, -15.48778, -41.98733],
							"uv": {
								"north": {"uv": [25, 0], "uv_size": [0.5, 0.5]},
								"east": {"uv": [1, 25], "uv_size": [0.5, 0.5]},
								"south": {"uv": [25, 1], "uv_size": [0.5, 0.5]},
								"west": {"uv": [2, 25], "uv_size": [0.5, 0.5]},
								"up": {"uv": [25, 2], "uv_size": [0.5, 0.5]},
								"down": {"uv": [3, 25.5], "uv_size": [0.5, -0.5]}
							}
						},
						{
							"origin": [-0.5655, -4.33355, 1.38446],
							"size": [1.129, 1.29941, 0.63517],
							"pivot": [-0.1, -3.84664, 2.01963],
							"rotation": [-22.5, 0, 0],
							"uv": {
								"north": {"uv": [2, 9], "uv_size": [1, 1.5]},
								"east": {"uv": [19, 16], "uv_size": [0.5, 1.5]},
								"south": {"uv": [9, 2], "uv_size": [1, 1.5]},
								"west": {"uv": [18, 19], "uv_size": [0.5, 1.5]},
								"up": {"uv": [9, 22], "uv_size": [1, 0.5]},
								"down": {"uv": [22, 9.5], "uv_size": [1, -0.5]}
							}
						},
						{
							"origin": [-0.3115, -3.10515, -0.59671],
							"size": [0.62201, 0.99878, 0.74363],
							"pivot": [0, -2.48137, 0.89692],
							"rotation": [-22.5, 0, 0],
							"uv": {
								"north": {"uv": [4, 22], "uv_size": [0.5, 1]},
								"east": {"uv": [22, 4], "uv_size": [0.5, 1]},
								"south": {"uv": [5, 22], "uv_size": [0.5, 1]},
								"west": {"uv": [22, 5], "uv_size": [0.5, 1]},
								"up": {"uv": [18, 24], "uv_size": [0.5, 0.5]},
								"down": {"uv": [24, 18.5], "uv_size": [0.5, -0.5]}
							}
						},
						{
							"origin": [-0.5625, -1.2625, -2.88079],
							"size": [1.125, 0.75, 0.75],
							"uv": {
								"north": {"uv": [11, 7], "uv_size": [1, 1]},
								"east": {"uv": [8, 11], "uv_size": [1, 1]},
								"south": {"uv": [11, 8], "uv_size": [1, 1]},
								"west": {"uv": [9, 11], "uv_size": [1, 1]},
								"up": {"uv": [10, 11], "uv_size": [1, 1]},
								"down": {"uv": [11, 12], "uv_size": [1, -1]}
							}
						},
						{
							"origin": [-0.6625, -0.6125, -2.48079],
							"size": [1.325, 0.25, 0.25],
							"pivot": [0, -0.4875, -2.35579],
							"rotation": [-45, 0, 0],
							"uv": {
								"north": {"uv": [15, 10], "uv_size": [1.5, 0.5]},
								"east": {"uv": [23, 11], "uv_size": [0.5, 0.5]},
								"south": {"uv": [11, 15], "uv_size": [1.5, 0.5]},
								"west": {"uv": [12, 23], "uv_size": [0.5, 0.5]},
								"up": {"uv": [15, 11], "uv_size": [1.5, 0.5]},
								"down": {"uv": [15, 12.5], "uv_size": [1.5, -0.5]}
							}
						},
						{
							"origin": [-0.6615, -0.8625, -2.51109],
							"size": [1.325, 0.15, 0.3106],
							"uv": {
								"north": {"uv": [14, 15], "uv_size": [1.5, 0.5]},
								"east": {"uv": [23, 12], "uv_size": [0.5, 0.5]},
								"south": {"uv": [16, 0], "uv_size": [1.5, 0.5]},
								"west": {"uv": [13, 23], "uv_size": [0.5, 0.5]},
								"up": {"uv": [16, 1], "uv_size": [1.5, 0.5]},
								"down": {"uv": [16, 2.5], "uv_size": [1.5, -0.5]}
							}
						},
						{
							"origin": [-0.6625, -0.2625, -2.51109],
							"size": [1.325, 0.15, 0.3106],
							"pivot": [0, -0.4875, -2.35579],
							"rotation": [45, 0, 0],
							"uv": {
								"north": {"uv": [16, 3], "uv_size": [1.5, 0.5]},
								"east": {"uv": [23, 13], "uv_size": [0.5, 0.5]},
								"south": {"uv": [4, 16], "uv_size": [1.5, 0.5]},
								"west": {"uv": [14, 23], "uv_size": [0.5, 0.5]},
								"up": {"uv": [16, 4], "uv_size": [1.5, 0.5]},
								"down": {"uv": [16, 6.5], "uv_size": [1.5, -0.5]}
							}
						},
						{
							"origin": [-0.6625, -0.6428, -2.73079],
							"size": [1.325, 0.3106, 0.15],
							"pivot": [0, -0.4875, -2.35579],
							"rotation": [45, 0, 0],
							"uv": {
								"north": {"uv": [16, 7], "uv_size": [1.5, 0.5]},
								"east": {"uv": [23, 14], "uv_size": [0.5, 0.5]},
								"south": {"uv": [16, 8], "uv_size": [1.5, 0.5]},
								"west": {"uv": [15, 23], "uv_size": [0.5, 0.5]},
								"up": {"uv": [16, 9], "uv_size": [1.5, 0.5]},
								"down": {"uv": [11, 16.5], "uv_size": [1.5, -0.5]}
							}
						},
						{
							"origin": [-0.6615, -0.6428, -2.13079],
							"size": [1.325, 0.3106, 0.15],
							"uv": {
								"north": {"uv": [13, 16], "uv_size": [1.5, 0.5]},
								"east": {"uv": [23, 15], "uv_size": [0.5, 0.5]},
								"south": {"uv": [16, 13], "uv_size": [1.5, 0.5]},
								"west": {"uv": [16, 23], "uv_size": [0.5, 0.5]},
								"up": {"uv": [16, 14], "uv_size": [1.5, 0.5]},
								"down": {"uv": [15, 16.5], "uv_size": [1.5, -0.5]}
							}
						},
						{
							"origin": [-0.6615, -0.2625, -2.51109],
							"size": [1.325, 0.15, 0.3106],
							"uv": {
								"north": {"uv": [16, 15], "uv_size": [1.5, 0.5]},
								"east": {"uv": [23, 16], "uv_size": [0.5, 0.5]},
								"south": {"uv": [0, 17], "uv_size": [1.5, 0.5]},
								"west": {"uv": [17, 23], "uv_size": [0.5, 0.5]},
								"up": {"uv": [2, 17], "uv_size": [1.5, 0.5]},
								"down": {"uv": [4, 17.5], "uv_size": [1.5, -0.5]}
							}
						},
						{
							"origin": [-0.6625, -0.8625, -2.51109],
							"size": [1.325, 0.15, 0.3106],
							"pivot": [0, -0.4875, -2.35579],
							"rotation": [45, 0, 0],
							"uv": {
								"north": {"uv": [17, 5], "uv_size": [1.5, 0.5]},
								"east": {"uv": [23, 17], "uv_size": [0.5, 0.5]},
								"south": {"uv": [6, 17], "uv_size": [1.5, 0.5]},
								"west": {"uv": [18, 23], "uv_size": [0.5, 0.5]},
								"up": {"uv": [8, 17], "uv_size": [1.5, 0.5]},
								"down": {"uv": [10, 17.5], "uv_size": [1.5, -0.5]}
							}
						},
						{
							"origin": [-0.6615, -0.6428, -2.73079],
							"size": [1.325, 0.3106, 0.15],
							"uv": {
								"north": {"uv": [17, 10], "uv_size": [1.5, 0.5]},
								"east": {"uv": [23, 18], "uv_size": [0.5, 0.5]},
								"south": {"uv": [17, 11], "uv_size": [1.5, 0.5]},
								"west": {"uv": [19, 23], "uv_size": [0.5, 0.5]},
								"up": {"uv": [12, 17], "uv_size": [1.5, 0.5]},
								"down": {"uv": [17, 12.5], "uv_size": [1.5, -0.5]}
							}
						},
						{
							"origin": [-0.6625, -0.6428, -2.13079],
							"size": [1.325, 0.3106, 0.15],
							"pivot": [0, -0.4875, -2.35579],
							"rotation": [45, 0, 0],
							"uv": {
								"north": {"uv": [14, 17], "uv_size": [1.5, 0.5]},
								"east": {"uv": [23, 19], "uv_size": [0.5, 0.5]},
								"south": {"uv": [16, 17], "uv_size": [1.5, 0.5]},
								"west": {"uv": [20, 23], "uv_size": [0.5, 0.5]},
								"up": {"uv": [17, 16], "uv_size": [1.5, 0.5]},
								"down": {"uv": [0, 18.5], "uv_size": [1.5, -0.5]}
							}
						},
						{
							"origin": [-0.3125, -1.5125, -2.88079],
							"size": [0.625, 0.25, 0.75],
							"uv": {
								"north": {"uv": [23, 20], "uv_size": [0.5, 0.5]},
								"east": {"uv": [21, 15], "uv_size": [1, 0.5]},
								"south": {"uv": [21, 23], "uv_size": [0.5, 0.5]},
								"west": {"uv": [16, 21], "uv_size": [1, 0.5]},
								"up": {"uv": [21, 16], "uv_size": [0.5, 1]},
								"down": {"uv": [17, 22], "uv_size": [0.5, -1]}
							}
						},
						{
							"origin": [0.15404, -1.46833, -2.88079],
							"size": [0.35355, 0.2317, 0.751],
							"pivot": [0.28659, -1.29913, -2.50579],
							"rotation": [0, 0, -45],
							"uv": {
								"north": {"uv": [23, 21], "uv_size": [0.5, 0.5]},
								"east": {"uv": [21, 17], "uv_size": [1, 0.5]},
								"south": {"uv": [22, 23], "uv_size": [0.5, 0.5]},
								"west": {"uv": [18, 21], "uv_size": [1, 0.5]},
								"up": {"uv": [21, 18], "uv_size": [0.5, 1]},
								"down": {"uv": [19, 22], "uv_size": [0.5, -1]}
							}
						},
						{
							"origin": [-0.50759, -1.46833, -2.88079],
							"size": [0.35355, 0.2317, 0.751],
							"pivot": [-0.28659, -1.29913, -2.50579],
							"rotation": [0, 0, 45],
							"uv": {
								"north": {"uv": [17, 24], "uv_size": [0.5, 0.5]},
								"east": {"uv": [2, 22], "uv_size": [1, 0.5]},
								"south": {"uv": [24, 17], "uv_size": [0.5, 0.5]},
								"west": {"uv": [22, 2], "uv_size": [1, 0.5]},
								"up": {"uv": [3, 22], "uv_size": [0.5, 1]},
								"down": {"uv": [22, 4], "uv_size": [0.5, -1]}
							}
						},
						{
							"origin": [-0.5615, -1.18956, -2.49748],
							"size": [1.123, 0.85, 0.6],
							"pivot": [0, -0.63956, -2.19748],
							"rotation": [-22.5, 0, 0],
							"uv": {
								"north": {"uv": [12, 0], "uv_size": [1, 1]},
								"east": {"uv": [21, 19], "uv_size": [0.5, 1]},
								"south": {"uv": [12, 1], "uv_size": [1, 1]},
								"west": {"uv": [20, 21], "uv_size": [0.5, 1]},
								"up": {"uv": [21, 20], "uv_size": [1, 0.5]},
								"down": {"uv": [21, 21.5], "uv_size": [1, -0.5]}
							}
						},
						{
							"origin": [-0.5605, -0.57734, -2.32555],
							"size": [1.121, 0.35, 0.85],
							"pivot": [0, -0.50234, -1.70055],
							"rotation": [45, 0, 0],
							"uv": {
								"north": {"uv": [0, 22], "uv_size": [1, 0.5]},
								"east": {"uv": [22, 0], "uv_size": [1, 0.5]},
								"south": {"uv": [1, 22], "uv_size": [1, 0.5]},
								"west": {"uv": [22, 1], "uv_size": [1, 0.5]},
								"up": {"uv": [12, 2], "uv_size": [1, 1]},
								"down": {"uv": [12, 4], "uv_size": [1, -1]}
							}
						}
					]
				}
			]
		}
	]
}